AUTHORS
MANIFEST.in
README.rst
run.py
setup.py
bullseye/__init__.py
bullseye/app.py
bullseye/bullseye.py
bullseye/capture.py
bullseye/dc1394_capture.py
bullseye/flycapture2_capture.py
bullseye/process.py
bullseye/replay_capture.py
bullseye/special_sums.py
bullseye.egg-info/PKG-INFO
bullseye.egg-info/SOURCES.txt
bullseye.egg-info/dependency_links.txt
bullseye.egg-info/entry_points.txt
bullseye.egg-info/namespace_packages.txt
bullseye.egg-info/requires.txt
bullseye.egg-info/top_level.txt
bullseye/tests/__init__.py