Metadata-Version: 1.0
Name: bullseye
Version: 0.1.1
Summary: laser beam profiler
Home-page: http://launchpad.net/pybullseye
Author: Robert Jordens
Author-email: jordens@phys.ethz.ch
License: GPLv3+
Platform: UNKNOWN
